co2/__init__.py
co2/cli/__init__.py
co2/cli/cli.py
co2/cli/plugins.py
co2/const.py
co2/formatter/__init__.py
co2/formatter/base.py
co2/utils/plugins.py
co2-0.5.0.dist-info/METADATA
co2-0.5.0.dist-info/WHEEL
co2-0.5.0.dist-info/entry_points.txt
co2-0.5.0.dist-info/RECORD
